flopi/__init__.py
flopi-0.0.2.dist-info/LICENSE
flopi-0.0.2.dist-info/METADATA
flopi-0.0.2.dist-info/WHEEL
flopi-0.0.2.dist-info/top_level.txt
flopi-0.0.2.dist-info/RECORD
