Metadata-Version: 2.1
Name: flopi
Version: 0.0.2
Summary: Fine-grained logging and output Python interface
Home-page: https://github.com/codecraftingtools/flopi
Author: Jeff Webb
Author-email: jeff.webb@codecraftsmen.org
License: UNKNOWN
Platform: UNKNOWN
Classifier: Programming Language :: Python :: 3
Classifier: License :: OSI Approved :: MIT License
Classifier: Operating System :: OS Independent
Requires-Python: >=3.6
